{
  "source": "bgtoll_weather",
  "schema_version": 1,
  "collector_version": "2.3.0",
  "collected_at": "2026-07-20T20:42:05.860Z",
  "official_page": "https://bgtoll.bg/mto/",
  "captured_from": "https://bgtoll.bg/index.php/mto/data",
  "records": [
    {
      "external_id": "1",
      "scp": "1001",
      "name": "Мотел Ихтиман",
      "latitude": 42.426981,
      "longitude": 23.854053,
      "temperature_air": 18.122564,
      "temperature_road": 23.821959,
      "humidity": 77.809204,
      "pressure": 937.277222,
      "wind_speed": 8.422749,
      "wind_direction": "18.207001",
      "precipitation": 0,
      "measured_at": "2026-07-20T20:30:00.000Z",
      "captured_from": "https://bgtoll.bg/index.php/mto/data",
      "source_extra": {
        "station_id": 1,
        "scp": 1001,
        "name": "Мотел Ихтиман",
        "nameENG": "Motel Ihtiman",
        "lat": 42.426981,
        "lon": 23.854053,
        "air": 18.122564,
        "surface": 23.821959,
        "humidity": 77.809204,
        "pressure": 937.277222,
        "wind": 8.422749,
        "wind_dir": 18.207001,
        "time": "2026-07-20 20:30:00"
      }
    },
    {
      "external_id": "11",
      "scp": "1010",
      "name": "Българчево",
      "latitude": 42.01164,
      "longitude": 23.044916,
      "temperature_air": 19.218422,
      "temperature_road": 26.27198,
      "humidity": 89.061867,
      "pressure": 979.364136,
      "wind_speed": 1.813551,
      "wind_direction": "23.382149",
      "precipitation": 0,
      "measured_at": "2026-07-20T20:30:00.000Z",
      "captured_from": "https://bgtoll.bg/index.php/mto/data",
      "source_extra": {
        "station_id": 11,
        "scp": 1010,
        "name": "Българчево",
        "nameENG": "Balgarchevo",
        "lat": 42.01164,
        "lon": 23.044916,
        "air": 19.218422,
        "surface": 26.27198,
        "humidity": 89.061867,
        "pressure": 979.364136,
        "wind": 1.813551,
        "wind_dir": 23.382149,
        "time": "2026-07-20 20:30:00"
      }
    },
    {
      "external_id": "116",
      "scp": "2032",
      "name": "Перник (кв. Църква)",
      "latitude": 42.573943,
      "longitude": 23.11752,
      "temperature_air": 16.697807,
      "temperature_road": 27.792997,
      "humidity": 89.111542,
      "pressure": 931.101013,
      "wind_speed": 7.544301,
      "wind_direction": "196.717529",
      "precipitation": 0,
      "measured_at": "2026-07-20T20:26:00.000Z",
      "captured_from": "https://bgtoll.bg/index.php/mto/data",
      "source_extra": {
        "station_id": 116,
        "scp": 2032,
        "name": "Перник (кв. Църква)",
        "nameENG": "Pernik (Tsarkva)",
        "lat": 42.573943,
        "lon": 23.11752,
        "air": 16.697807,
        "surface": 27.792997,
        "humidity": 89.111542,
        "pressure": 931.101013,
        "wind": 7.544301,
        "wind_dir": 196.717529,
        "time": "2026-07-20 20:26:00"
      }
    },
    {
      "external_id": "117",
      "scp": "2033",
      "name": "Дяково",
      "latitude": 42.324184,
      "longitude": 23.095974,
      "temperature_air": 17.592188,
      "temperature_road": 26.173319,
      "humidity": 91.592888,
      "pressure": 948.958679,
      "wind_speed": 3.396856,
      "wind_direction": "339.757599",
      "precipitation": 0,
      "measured_at": "2026-07-20T20:26:00.000Z",
      "captured_from": "https://bgtoll.bg/index.php/mto/data",
      "source_extra": {
        "station_id": 117,
        "scp": 2033,
        "name": "Дяково",
        "nameENG": "Dyakovo",
        "lat": 42.324184,
        "lon": 23.095974,
        "air": 17.592188,
        "surface": 26.173319,
        "humidity": 91.592888,
        "pressure": 948.958679,
        "wind": 3.396856,
        "wind_dir": 339.757599,
        "time": "2026-07-20 20:26:00"
      }
    },
    {
      "external_id": "119",
      "scp": "2042",
      "name": "Тунел Мало Бучино",
      "latitude": 42.677658,
      "longitude": 23.152263,
      "temperature_air": 16.470348,
      "temperature_road": 0,
      "humidity": 86.034248,
      "pressure": 926.650635,
      "wind_speed": 11.058298,
      "wind_direction": "181.961365",
      "precipitation": 0,
      "measured_at": "2026-07-20T20:26:00.000Z",
      "captured_from": "https://bgtoll.bg/index.php/mto/data",
      "source_extra": {
        "station_id": 119,
        "scp": 2042,
        "name": "Тунел Мало Бучино",
        "nameENG": "Tunnel Malo Buchino",
        "lat": 42.677658,
        "lon": 23.152263,
        "air": 16.470348,
        "surface": 0,
        "humidity": 86.034248,
        "pressure": 926.650635,
        "wind": 11.058298,
        "wind_dir": 181.961365,
        "time": "2026-07-20 20:26:00"
      }
    },
    {
      "external_id": "12",
      "scp": "1011",
      "name": "Марикостиново",
      "latitude": 41.419104,
      "longitude": 23.33396,
      "temperature_air": 24.975401,
      "temperature_road": 35.735184,
      "humidity": 58.186928,
      "pressure": 1005.738159,
      "wind_speed": 21.977972,
      "wind_direction": "290.408417",
      "precipitation": 0,
      "measured_at": "2026-07-20T20:16:00.000Z",
      "captured_from": "https://bgtoll.bg/index.php/mto/data",
      "source_extra": {
        "station_id": 12,
        "scp": 1011,
        "name": "Марикостиново",
        "nameENG": "Marikostinovo",
        "lat": 41.419104,
        "lon": 23.33396,
        "air": 24.975401,
        "surface": 35.735184,
        "humidity": 58.186928,
        "pressure": 1005.738159,
        "wind": 21.977972,
        "wind_dir": 290.408417,
        "time": "2026-07-20 20:16:00"
      }
    },
    {
      "external_id": "120",
      "scp": "2056",
      "name": "Обход Враца",
      "latitude": 43.243474,
      "longitude": 23.565115,
      "temperature_air": 24.786827,
      "temperature_road": 0,
      "humidity": 56.120716,
      "pressure": 980.838379,
      "wind_speed": 1.944711,
      "wind_direction": "14.986511",
      "precipitation": 0,
      "measured_at": "2026-07-20T20:26:00.000Z",
      "captured_from": "https://bgtoll.bg/index.php/mto/data",
      "source_extra": {
        "station_id": 120,
        "scp": 2056,
        "name": "Обход Враца",
        "nameENG": "bypass Vratsa",
        "lat": 43.243474,
        "lon": 23.565115,
        "air": 24.786827,
        "surface": 0,
        "humidity": 56.120716,
        "pressure": 980.838379,
        "wind": 1.944711,
        "wind_dir": 14.986511,
        "time": "2026-07-20 20:26:00"
      }
    },
    {
      "external_id": "123",
      "scp": "2082",
      "name": "Димитровград",
      "latitude": 42.038769,
      "longitude": 25.578869,
      "temperature_air": 19.753258,
      "temperature_road": 33.920387,
      "humidity": 100,
      "pressure": 1001.662842,
      "wind_speed": 38.111366,
      "wind_direction": "336.520752",
      "precipitation": 0,
      "measured_at": "2026-07-20T20:26:00.000Z",
      "captured_from": "https://bgtoll.bg/index.php/mto/data",
      "source_extra": {
        "station_id": 123,
        "scp": 2082,
        "name": "Димитровград",
        "nameENG": "Dimitrovgrad",
        "lat": 42.038769,
        "lon": 25.578869,
        "air": 19.753258,
        "surface": 33.920387,
        "humidity": 100,
        "pressure": 1001.662842,
        "wind": 38.111366,
        "wind_dir": 336.520752,
        "time": "2026-07-20 20:26:00"
      }
    },
    {
      "external_id": "124",
      "scp": "2090",
      "name": "Равда",
      "latitude": 42.654704,
      "longitude": 27.674976,
      "temperature_air": 24.843758,
      "temperature_road": 0,
      "humidity": 78.767906,
      "pressure": 1010.927185,
      "wind_speed": 7.687889,
      "wind_direction": "129.0802",
      "precipitation": 0,
      "measured_at": "2026-07-20T20:26:00.000Z",
      "captured_from": "https://bgtoll.bg/index.php/mto/data",
      "source_extra": {
        "station_id": 124,
        "scp": 2090,
        "name": "Равда",
        "nameENG": "Ravda",
        "lat": 42.654704,
        "lon": 27.674976,
        "air": 24.843758,
        "surface": 0,
        "humidity": 78.767906,
        "pressure": 1010.927185,
        "wind": 7.687889,
        "wind_dir": 129.0802,
        "time": "2026-07-20 20:26:00"
      }
    },
    {
      "external_id": "125",
      "scp": "2100",
      "name": "Пчелиново",
      "latitude": 42.704528,
      "longitude": 25.737056,
      "temperature_air": 21.231489,
      "temperature_road": 28.609217,
      "humidity": 85.446236,
      "pressure": 973.248962,
      "wind_speed": 2.485321,
      "wind_direction": "279.397949",
      "precipitation": 0,
      "measured_at": "2026-07-20T20:27:00.000Z",
      "captured_from": "https://bgtoll.bg/index.php/mto/data",
      "source_extra": {
        "station_id": 125,
        "scp": 2100,
        "name": "Пчелиново",
        "nameENG": "Pchelinovo",
        "lat": 42.704528,
        "lon": 25.737056,
        "air": 21.231489,
        "surface": 28.609217,
        "humidity": 85.446236,
        "pressure": 973.248962,
        "wind": 2.485321,
        "wind_dir": 279.397949,
        "time": "2026-07-20 20:27:00"
      }
    },
    {
      "external_id": "126",
      "scp": "3005",
      "name": "Борован",
      "latitude": 43.42857,
      "longitude": 23.77569,
      "temperature_air": 24.514107,
      "temperature_road": 34.002602,
      "humidity": 56.049713,
      "pressure": 992.457275,
      "wind_speed": 1.481351,
      "wind_direction": "340.18457",
      "precipitation": 0,
      "measured_at": "2026-07-20T20:27:00.000Z",
      "captured_from": "https://bgtoll.bg/index.php/mto/data",
      "source_extra": {
        "station_id": 126,
        "scp": 3005,
        "name": "Борован",
        "nameENG": "Borovan",
        "lat": 43.42857,
        "lon": 23.77569,
        "air": 24.514107,
        "surface": 34.002602,
        "humidity": 56.049713,
        "pressure": 992.457275,
        "wind": 1.481351,
        "wind_dir": 340.18457,
        "time": "2026-07-20 20:27:00"
      }
    },
    {
      "external_id": "128",
      "scp": "3042",
      "name": "Попово",
      "latitude": 43.35071,
      "longitude": 26.20077,
      "temperature_air": 21.528738,
      "temperature_road": 0,
      "humidity": 81.492714,
      "pressure": 991.738586,
      "wind_speed": 0,
      "wind_direction": "0",
      "precipitation": 0,
      "measured_at": "2026-07-20T20:27:00.000Z",
      "captured_from": "https://bgtoll.bg/index.php/mto/data",
      "source_extra": {
        "station_id": 128,
        "scp": 3042,
        "name": "Попово",
        "nameENG": "Popovo",
        "lat": 43.35071,
        "lon": 26.20077,
        "air": 21.528738,
        "surface": 0,
        "humidity": 81.492714,
        "pressure": 991.738586,
        "wind": 0,
        "wind_dir": 0,
        "time": "2026-07-20 20:27:00"
      }
    },
    {
      "external_id": "13",
      "scp": "1012",
      "name": "Покровник",
      "latitude": 41.991957,
      "longitude": 23.053976,
      "temperature_air": 19.43763,
      "temperature_road": 27.586287,
      "humidity": 84.782364,
      "pressure": 979.412903,
      "wind_speed": 3.853924,
      "wind_direction": "135.911194",
      "precipitation": 0,
      "measured_at": "2026-07-20T20:16:00.000Z",
      "captured_from": "https://bgtoll.bg/index.php/mto/data",
      "source_extra": {
        "station_id": 13,
        "scp": 1012,
        "name": "Покровник",
        "nameENG": "Pokrovnik",
        "lat": 41.991957,
        "lon": 23.053976,
        "air": 19.43763,
        "surface": 27.586287,
        "humidity": 84.782364,
        "pressure": 979.412903,
        "wind": 3.853924,
        "wind_dir": 135.911194,
        "time": "2026-07-20 20:16:00"
      }
    },
    {
      "external_id": "130",
      "scp": "3059",
      "name": "Пиперков Чифлик",
      "latitude": 42.2776,
      "longitude": 22.74289,
      "temperature_air": 17.006744,
      "temperature_road": 29.005974,
      "humidity": 91.49456,
      "pressure": 961.95929,
      "wind_speed": 3.36644,
      "wind_direction": "179.556992",
      "precipitation": 0,
      "measured_at": "2026-07-20T20:27:00.000Z",
      "captured_from": "https://bgtoll.bg/index.php/mto/data",
      "source_extra": {
        "station_id": 130,
        "scp": 3059,
        "name": "Пиперков Чифлик",
        "nameENG": "Piperkov Chiflik",
        "lat": 42.2776,
        "lon": 22.74289,
        "air": 17.006744,
        "surface": 29.005974,
        "humidity": 91.49456,
        "pressure": 961.95929,
        "wind": 3.36644,
        "wind_dir": 179.556992,
        "time": "2026-07-20 20:27:00"
      }
    },
    {
      "external_id": "131",
      "scp": "3075",
      "name": "село Добрич",
      "latitude": 42.16906,
      "longitude": 26.66235,
      "temperature_air": 22.95923,
      "temperature_road": 34.437286,
      "humidity": 80.318512,
      "pressure": 1000.587952,
      "wind_speed": 0,
      "wind_direction": "0",
      "precipitation": 0,
      "measured_at": "2026-07-20T20:27:00.000Z",
      "captured_from": "https://bgtoll.bg/index.php/mto/data",
      "source_extra": {
        "station_id": 131,
        "scp": 3075,
        "name": "село Добрич",
        "nameENG": "village Dobrich",
        "lat": 42.16906,
        "lon": 26.66235,
        "air": 22.95923,
        "surface": 34.437286,
        "humidity": 80.318512,
        "pressure": 1000.587952,
        "wind": 0,
        "wind_dir": 0,
        "time": "2026-07-20 20:27:00"
      }
    },
    {
      "external_id": "132",
      "scp": "3084",
      "name": "гара Костандово",
      "latitude": 42.03532,
      "longitude": 24.07068,
      "temperature_air": 17.10885,
      "temperature_road": 24.097702,
      "humidity": 94.650467,
      "pressure": 928.41272,
      "wind_speed": 1.946321,
      "wind_direction": "190.417908",
      "precipitation": 0,
      "measured_at": "2026-07-20T20:27:00.000Z",
      "captured_from": "https://bgtoll.bg/index.php/mto/data",
      "source_extra": {
        "station_id": 132,
        "scp": 3084,
        "name": "гара Костандово",
        "nameENG": "rail station Kostandovo",
        "lat": 42.03532,
        "lon": 24.07068,
        "air": 17.10885,
        "surface": 24.097702,
        "humidity": 94.650467,
        "pressure": 928.41272,
        "wind": 1.946321,
        "wind_dir": 190.417908,
        "time": "2026-07-20 20:27:00"
      }
    },
    {
      "external_id": "134",
      "scp": "3099",
      "name": "Петрич",
      "latitude": 41.44541,
      "longitude": 23.21762,
      "temperature_air": 24.358671,
      "temperature_road": 31.124594,
      "humidity": 59.654652,
      "pressure": 1005.324463,
      "wind_speed": 3.599958,
      "wind_direction": "357.495697",
      "precipitation": 0,
      "measured_at": "2026-07-20T20:27:00.000Z",
      "captured_from": "https://bgtoll.bg/index.php/mto/data",
      "source_extra": {
        "station_id": 134,
        "scp": 3099,
        "name": "Петрич",
        "nameENG": "Petrich",
        "lat": 41.44541,
        "lon": 23.21762,
        "air": 24.358671,
        "surface": 31.124594,
        "humidity": 59.654652,
        "pressure": 1005.324463,
        "wind": 3.599958,
        "wind_dir": 357.495697,
        "time": "2026-07-20 20:27:00"
      }
    },
    {
      "external_id": "135",
      "scp": "3102",
      "name": "Петрич",
      "latitude": 41.39665,
      "longitude": 23.17111,
      "temperature_air": 22.858698,
      "temperature_road": 34.29631,
      "humidity": 72.517227,
      "pressure": 1000.812683,
      "wind_speed": 11.372936,
      "wind_direction": "129.579926",
      "precipitation": 0,
      "measured_at": "2026-07-20T20:28:00.000Z",
      "captured_from": "https://bgtoll.bg/index.php/mto/data",
      "source_extra": {
        "station_id": 135,
        "scp": 3102,
        "name": "Петрич",
        "nameENG": "Petrich",
        "lat": 41.39665,
        "lon": 23.17111,
        "air": 22.858698,
        "surface": 34.29631,
        "humidity": 72.517227,
        "pressure": 1000.812683,
        "wind": 11.372936,
        "wind_dir": 129.579926,
        "time": "2026-07-20 20:28:00"
      }
    },
    {
      "external_id": "136",
      "scp": "3103",
      "name": "Разград",
      "latitude": 43.52144,
      "longitude": 26.48714,
      "temperature_air": 20.844652,
      "temperature_road": 28.010351,
      "humidity": 86.016045,
      "pressure": 992.140198,
      "wind_speed": 0,
      "wind_direction": "0",
      "precipitation": 0,
      "measured_at": "2026-07-20T20:28:00.000Z",
      "captured_from": "https://bgtoll.bg/index.php/mto/data",
      "source_extra": {
        "station_id": 136,
        "scp": 3103,
        "name": "Разград",
        "nameENG": "Razgrad",
        "lat": 43.52144,
        "lon": 26.48714,
        "air": 20.844652,
        "surface": 28.010351,
        "humidity": 86.016045,
        "pressure": 992.140198,
        "wind": 0,
        "wind_dir": 0,
        "time": "2026-07-20 20:28:00"
      }
    },
    {
      "external_id": "138",
      "scp": "4014",
      "name": "Ряховците",
      "latitude": 43.033159,
      "longitude": 25.010429,
      "temperature_air": 24.961748,
      "temperature_road": 0,
      "humidity": 62.106754,
      "pressure": 987.428711,
      "wind_speed": 5.625363,
      "wind_direction": "290.978394",
      "precipitation": 0,
      "measured_at": "2026-07-20T20:28:00.000Z",
      "captured_from": "https://bgtoll.bg/index.php/mto/data",
      "source_extra": {
        "station_id": 138,
        "scp": 4014,
        "name": "Ряховците",
        "nameENG": "Ryahovtsite",
        "lat": 43.033159,
        "lon": 25.010429,
        "air": 24.961748,
        "surface": 0,
        "humidity": 62.106754,
        "pressure": 987.428711,
        "wind": 5.625363,
        "wind_dir": 290.978394,
        "time": "2026-07-20 20:28:00"
      }
    },
    {
      "external_id": "139",
      "scp": "4018",
      "name": "Шумен",
      "latitude": 43.317481,
      "longitude": 26.920131,
      "temperature_air": 20.179714,
      "temperature_road": 26.880733,
      "humidity": 95.410873,
      "pressure": 990.493347,
      "wind_speed": 2.915547,
      "wind_direction": "329.565918",
      "precipitation": 0,
      "measured_at": "2026-07-20T20:28:00.000Z",
      "captured_from": "https://bgtoll.bg/index.php/mto/data",
      "source_extra": {
        "station_id": 139,
        "scp": 4018,
        "name": "Шумен",
        "nameENG": "Shumen",
        "lat": 43.317481,
        "lon": 26.920131,
        "air": 20.179714,
        "surface": 26.880733,
        "humidity": 95.410873,
        "pressure": 990.493347,
        "wind": 2.915547,
        "wind_dir": 329.565918,
        "time": "2026-07-20 20:28:00"
      }
    },
    {
      "external_id": "141",
      "scp": "4027",
      "name": "Богатово",
      "latitude": 43.042734,
      "longitude": 25.215309,
      "temperature_air": 24.266914,
      "temperature_road": 30.067194,
      "humidity": 64.494926,
      "pressure": 978.822388,
      "wind_speed": 2.928492,
      "wind_direction": "10.965027",
      "precipitation": 0,
      "measured_at": "2026-07-20T20:28:00.000Z",
      "captured_from": "https://bgtoll.bg/index.php/mto/data",
      "source_extra": {
        "station_id": 141,
        "scp": 4027,
        "name": "Богатово",
        "nameENG": "Bogatovo",
        "lat": 43.042734,
        "lon": 25.215309,
        "air": 24.266914,
        "surface": 30.067194,
        "humidity": 64.494926,
        "pressure": 978.822388,
        "wind": 2.928492,
        "wind_dir": 10.965027,
        "time": "2026-07-20 20:28:00"
      }
    },
    {
      "external_id": "143",
      "scp": "4033",
      "name": "ДЗС",
      "latitude": 43.777364,
      "longitude": 26.01985,
      "temperature_air": 23.551104,
      "temperature_road": 0,
      "humidity": 68.761139,
      "pressure": 996.541077,
      "wind_speed": 3.60423,
      "wind_direction": "263.7146",
      "precipitation": 0,
      "measured_at": "2026-07-20T20:28:00.000Z",
      "captured_from": "https://bgtoll.bg/index.php/mto/data",
      "source_extra": {
        "station_id": 143,
        "scp": 4033,
        "name": "ДЗС",
        "nameENG": "DZS",
        "lat": 43.777364,
        "lon": 26.01985,
        "air": 23.551104,
        "surface": 0,
        "humidity": 68.761139,
        "pressure": 996.541077,
        "wind": 3.60423,
        "wind_dir": 263.7146,
        "time": "2026-07-20 20:28:00"
      }
    },
    {
      "external_id": "144",
      "scp": "4040",
      "name": "Крън",
      "latitude": 42.653958,
      "longitude": 25.379942,
      "temperature_air": 24.932718,
      "temperature_road": 29.849293,
      "humidity": 65.756859,
      "pressure": 969.342224,
      "wind_speed": 6.64433,
      "wind_direction": "200.458984",
      "precipitation": 0,
      "measured_at": "2026-07-20T20:28:00.000Z",
      "captured_from": "https://bgtoll.bg/index.php/mto/data",
      "source_extra": {
        "station_id": 144,
        "scp": 4040,
        "name": "Крън",
        "nameENG": "Kran",
        "lat": 42.653958,
        "lon": 25.379942,
        "air": 24.932718,
        "surface": 29.849293,
        "humidity": 65.756859,
        "pressure": 969.342224,
        "wind": 6.64433,
        "wind_dir": 200.458984,
        "time": "2026-07-20 20:28:00"
      }
    },
    {
      "external_id": "145",
      "scp": "4059",
      "name": "Миланово",
      "latitude": 43.181897,
      "longitude": 26.857028,
      "temperature_air": 23.213083,
      "temperature_road": 26.299274,
      "humidity": 90.93383,
      "pressure": 1004.591797,
      "wind_speed": 0,
      "wind_direction": "0",
      "precipitation": 0,
      "measured_at": "2026-07-20T20:29:00.000Z",
      "captured_from": "https://bgtoll.bg/index.php/mto/data",
      "source_extra": {
        "station_id": 145,
        "scp": 4059,
        "name": "Миланово",
        "nameENG": "Milanovo",
        "lat": 43.181897,
        "lon": 26.857028,
        "air": 23.213083,
        "surface": 26.299274,
        "humidity": 90.93383,
        "pressure": 1004.591797,
        "wind": 0,
        "wind_dir": 0,
        "time": "2026-07-20 20:29:00"
      }
    },
    {
      "external_id": "147",
      "scp": "4090",
      "name": "Айдемир",
      "latitude": 44.097796,
      "longitude": 27.1357,
      "temperature_air": 23.930553,
      "temperature_road": 31.249903,
      "humidity": 82.088318,
      "pressure": 1006.401855,
      "wind_speed": 2.106401,
      "wind_direction": "225.021698",
      "precipitation": 0,
      "measured_at": "2026-07-20T20:29:00.000Z",
      "captured_from": "https://bgtoll.bg/index.php/mto/data",
      "source_extra": {
        "station_id": 147,
        "scp": 4090,
        "name": "Айдемир",
        "nameENG": "Aydemir",
        "lat": 44.097796,
        "lon": 27.1357,
        "air": 23.930553,
        "surface": 31.249903,
        "humidity": 82.088318,
        "pressure": 1006.401855,
        "wind": 2.106401,
        "wind_dir": 225.021698,
        "time": "2026-07-20 20:29:00"
      }
    },
    {
      "external_id": "148",
      "scp": "2058",
      "name": "Казанлък",
      "latitude": 42.61357,
      "longitude": 25.43539,
      "temperature_air": 23.630604,
      "temperature_road": 0,
      "humidity": 71.78138,
      "pressure": 975.016907,
      "wind_speed": 3.52895,
      "wind_direction": "210.802185",
      "precipitation": 0,
      "measured_at": "2026-07-20T20:29:00.000Z",
      "captured_from": "https://bgtoll.bg/index.php/mto/data",
      "source_extra": {
        "station_id": 148,
        "scp": 2058,
        "name": "Казанлък",
        "nameENG": "Kazanlak",
        "lat": 42.61357,
        "lon": 25.43539,
        "air": 23.630604,
        "surface": 0,
        "humidity": 71.78138,
        "pressure": 975.016907,
        "wind": 3.52895,
        "wind_dir": 210.802185,
        "time": "2026-07-20 20:29:00"
      }
    },
    {
      "external_id": "149",
      "scp": "4010",
      "name": "Блатино",
      "latitude": 42.294561,
      "longitude": 23.116097,
      "temperature_air": 17.848066,
      "temperature_road": 27.00366,
      "humidity": 84.576347,
      "pressure": 955.149475,
      "wind_speed": 12.326129,
      "wind_direction": "153.390076",
      "precipitation": 0,
      "measured_at": "2026-07-20T20:29:00.000Z",
      "captured_from": "https://bgtoll.bg/index.php/mto/data",
      "source_extra": {
        "station_id": 149,
        "scp": 4010,
        "name": "Блатино",
        "nameENG": "Blatino",
        "lat": 42.294561,
        "lon": 23.116097,
        "air": 17.848066,
        "surface": 27.00366,
        "humidity": 84.576347,
        "pressure": 955.149475,
        "wind": 12.326129,
        "wind_dir": 153.390076,
        "time": "2026-07-20 20:29:00"
      }
    },
    {
      "external_id": "15",
      "scp": "1014",
      "name": "Сандански",
      "latitude": 41.573272,
      "longitude": 23.239554,
      "temperature_air": 23.424517,
      "temperature_road": 28.372974,
      "humidity": 68.816902,
      "pressure": 1004.652832,
      "wind_speed": 6.369934,
      "wind_direction": "13.2211",
      "precipitation": 0,
      "measured_at": "2026-07-20T20:16:00.000Z",
      "captured_from": "https://bgtoll.bg/index.php/mto/data",
      "source_extra": {
        "station_id": 15,
        "scp": 1014,
        "name": "Сандански",
        "nameENG": "Sandanski",
        "lat": 41.573272,
        "lon": 23.239554,
        "air": 23.424517,
        "surface": 28.372974,
        "humidity": 68.816902,
        "pressure": 1004.652832,
        "wind": 6.369934,
        "wind_dir": 13.2211,
        "time": "2026-07-20 20:16:00"
      }
    },
    {
      "external_id": "150",
      "scp": "4037",
      "name": "Соколово",
      "latitude": 43.018519,
      "longitude": 25.528069,
      "temperature_air": 21.4303,
      "temperature_road": 28.091795,
      "humidity": 85.352661,
      "pressure": 994.639526,
      "wind_speed": 0,
      "wind_direction": "0",
      "precipitation": 0,
      "measured_at": "2026-07-20T20:29:00.000Z",
      "captured_from": "https://bgtoll.bg/index.php/mto/data",
      "source_extra": {
        "station_id": 150,
        "scp": 4037,
        "name": "Соколово",
        "nameENG": "Sokolovo",
        "lat": 43.018519,
        "lon": 25.528069,
        "air": 21.4303,
        "surface": 28.091795,
        "humidity": 85.352661,
        "pressure": 994.639526,
        "wind": 0,
        "wind_dir": 0,
        "time": "2026-07-20 20:29:00"
      }
    },
    {
      "external_id": "151",
      "scp": "4057",
      "name": "Алфатар",
      "latitude": 43.955417,
      "longitude": 27.294458,
      "temperature_air": 22.088661,
      "temperature_road": 30.234884,
      "humidity": 89.343231,
      "pressure": 994.514893,
      "wind_speed": 4.015526,
      "wind_direction": "127.253914",
      "precipitation": 0,
      "measured_at": "2026-07-20T20:29:00.000Z",
      "captured_from": "https://bgtoll.bg/index.php/mto/data",
      "source_extra": {
        "station_id": 151,
        "scp": 4057,
        "name": "Алфатар",
        "nameENG": "Alfatar",
        "lat": 43.955417,
        "lon": 27.294458,
        "air": 22.088661,
        "surface": 30.234884,
        "humidity": 89.343231,
        "pressure": 994.514893,
        "wind": 4.015526,
        "wind_dir": 127.253914,
        "time": "2026-07-20 20:29:00"
      }
    },
    {
      "external_id": "152",
      "scp": "2050",
      "name": "Поликраище",
      "latitude": 43.189481,
      "longitude": 25.621917,
      "temperature_air": 25.465839,
      "temperature_road": 0,
      "humidity": 60.433578,
      "pressure": 1007.105713,
      "wind_speed": 4.289017,
      "wind_direction": "231.991608",
      "precipitation": 0,
      "measured_at": "2026-07-20T20:29:00.000Z",
      "captured_from": "https://bgtoll.bg/index.php/mto/data",
      "source_extra": {
        "station_id": 152,
        "scp": 2050,
        "name": "Поликраище",
        "nameENG": "Polikraishte",
        "lat": 43.189481,
        "lon": 25.621917,
        "air": 25.465839,
        "surface": 0,
        "humidity": 60.433578,
        "pressure": 1007.105713,
        "wind": 4.289017,
        "wind_dir": 231.991608,
        "time": "2026-07-20 20:29:00"
      }
    },
    {
      "external_id": "153",
      "scp": "3067",
      "name": "Богорово",
      "latitude": 44.016423,
      "longitude": 27.364475,
      "temperature_air": 23.29554,
      "temperature_road": 27.322861,
      "humidity": 85.163895,
      "pressure": 1010.00885,
      "wind_speed": 1.251327,
      "wind_direction": "211.983276",
      "precipitation": 0,
      "measured_at": "2026-07-20T20:29:00.000Z",
      "captured_from": "https://bgtoll.bg/index.php/mto/data",
      "source_extra": {
        "station_id": 153,
        "scp": 3067,
        "name": "Богорово",
        "nameENG": "Bogorovo",
        "lat": 44.016423,
        "lon": 27.364475,
        "air": 23.29554,
        "surface": 27.322861,
        "humidity": 85.163895,
        "pressure": 1010.00885,
        "wind": 1.251327,
        "wind_dir": 211.983276,
        "time": "2026-07-20 20:29:00"
      }
    },
    {
      "external_id": "154",
      "scp": "3098",
      "name": "Кочериново",
      "latitude": 42.0916,
      "longitude": 23.0686,
      "temperature_air": 18.663179,
      "temperature_road": 25.856306,
      "humidity": 90.436958,
      "pressure": 970.126099,
      "wind_speed": 2.360458,
      "wind_direction": "14.061249",
      "precipitation": 0,
      "measured_at": "2026-07-20T20:29:00.000Z",
      "captured_from": "https://bgtoll.bg/index.php/mto/data",
      "source_extra": {
        "station_id": 154,
        "scp": 3098,
        "name": "Кочериново",
        "nameENG": "Kocherinovo",
        "lat": 42.0916,
        "lon": 23.0686,
        "air": 18.663179,
        "surface": 25.856306,
        "humidity": 90.436958,
        "pressure": 970.126099,
        "wind": 2.360458,
        "wind_dir": 14.061249,
        "time": "2026-07-20 20:29:00"
      }
    },
    {
      "external_id": "17",
      "scp": "1016",
      "name": "Харманли",
      "latitude": 41.957749,
      "longitude": 25.882525,
      "temperature_air": 26.622623,
      "temperature_road": 34.75745,
      "humidity": 64.453178,
      "pressure": 1004.2099,
      "wind_speed": 3.009974,
      "wind_direction": "139.929688",
      "precipitation": 0,
      "measured_at": "2026-07-20T20:16:00.000Z",
      "captured_from": "https://bgtoll.bg/index.php/mto/data",
      "source_extra": {
        "station_id": 17,
        "scp": 1016,
        "name": "Харманли",
        "nameENG": "Harmanli",
        "lat": 41.957749,
        "lon": 25.882525,
        "air": 26.622623,
        "surface": 34.75745,
        "humidity": 64.453178,
        "pressure": 1004.2099,
        "wind": 3.009974,
        "wind_dir": 139.929688,
        "time": "2026-07-20 20:16:00"
      }
    },
    {
      "external_id": "18",
      "scp": "1017",
      "name": "Звездица",
      "latitude": 43.152241,
      "longitude": 27.826223,
      "temperature_air": 21.970303,
      "temperature_road": 28.274818,
      "humidity": 84.210526,
      "pressure": 993.190063,
      "wind_speed": 5.968058,
      "wind_direction": "152.262772",
      "precipitation": 0,
      "measured_at": "2026-07-20T20:16:00.000Z",
      "captured_from": "https://bgtoll.bg/index.php/mto/data",
      "source_extra": {
        "station_id": 18,
        "scp": 1017,
        "name": "Звездица",
        "nameENG": "Zvezditsa",
        "lat": 43.152241,
        "lon": 27.826223,
        "air": 21.970303,
        "surface": 28.274818,
        "humidity": 84.210526,
        "pressure": 993.190063,
        "wind": 5.968058,
        "wind_dir": 152.262772,
        "time": "2026-07-20 20:16:00"
      }
    },
    {
      "external_id": "21",
      "scp": "1019",
      "name": "Чепинци",
      "latitude": 42.719517,
      "longitude": 23.400456,
      "temperature_air": 18.72345,
      "temperature_road": 24.325611,
      "humidity": 84.133339,
      "pressure": 957.674011,
      "wind_speed": 2.541116,
      "wind_direction": "204.638123",
      "precipitation": 0,
      "measured_at": "2026-07-20T20:16:00.000Z",
      "captured_from": "https://bgtoll.bg/index.php/mto/data",
      "source_extra": {
        "station_id": 21,
        "scp": 1019,
        "name": "Чепинци",
        "nameENG": "Chepintsi",
        "lat": 42.719517,
        "lon": 23.400456,
        "air": 18.72345,
        "surface": 24.325611,
        "humidity": 84.133339,
        "pressure": 957.674011,
        "wind": 2.541116,
        "wind_dir": 204.638123,
        "time": "2026-07-20 20:16:00"
      }
    },
    {
      "external_id": "35",
      "scp": "1031",
      "name": "Малко Чочовени",
      "latitude": 42.634585,
      "longitude": 26.212107,
      "temperature_air": 21.522251,
      "temperature_road": 32.176163,
      "humidity": 85.387794,
      "pressure": 994.737915,
      "wind_speed": 3.133512,
      "wind_direction": "214.913818",
      "precipitation": 0,
      "measured_at": "2026-07-20T20:18:00.000Z",
      "captured_from": "https://bgtoll.bg/index.php/mto/data",
      "source_extra": {
        "station_id": 35,
        "scp": 1031,
        "name": "Малко Чочовени",
        "nameENG": "Malko Chochoveni",
        "lat": 42.634585,
        "lon": 26.212107,
        "air": 21.522251,
        "surface": 32.176163,
        "humidity": 85.387794,
        "pressure": 994.737915,
        "wind": 3.133512,
        "wind_dir": 214.913818,
        "time": "2026-07-20 20:18:00"
      }
    },
    {
      "external_id": "36",
      "scp": "1032",
      "name": "Ветрен",
      "latitude": 42.605309,
      "longitude": 25.631865,
      "temperature_air": 25.763739,
      "temperature_road": 31.724192,
      "humidity": 64.227249,
      "pressure": 980.986267,
      "wind_speed": 7.385182,
      "wind_direction": "269.401367",
      "precipitation": 0,
      "measured_at": "2026-07-20T20:18:00.000Z",
      "captured_from": "https://bgtoll.bg/index.php/mto/data",
      "source_extra": {
        "station_id": 36,
        "scp": 1032,
        "name": "Ветрен",
        "nameENG": "Vetren",
        "lat": 42.605309,
        "lon": 25.631865,
        "air": 25.763739,
        "surface": 31.724192,
        "humidity": 64.227249,
        "pressure": 980.986267,
        "wind": 7.385182,
        "wind_dir": 269.401367,
        "time": "2026-07-20 20:18:00"
      }
    },
    {
      "external_id": "37",
      "scp": "1033",
      "name": "Карнобат",
      "latitude": 42.654112,
      "longitude": 27.008792,
      "temperature_air": 21.20656,
      "temperature_road": 32.941616,
      "humidity": 92.55201,
      "pressure": 992.064514,
      "wind_speed": 3.0249,
      "wind_direction": "268.551971",
      "precipitation": 0,
      "measured_at": "2026-07-20T20:18:00.000Z",
      "captured_from": "https://bgtoll.bg/index.php/mto/data",
      "source_extra": {
        "station_id": 37,
        "scp": 1033,
        "name": "Карнобат",
        "nameENG": "Karnobat",
        "lat": 42.654112,
        "lon": 27.008792,
        "air": 21.20656,
        "surface": 32.941616,
        "humidity": 92.55201,
        "pressure": 992.064514,
        "wind": 3.0249,
        "wind_dir": 268.551971,
        "time": "2026-07-20 20:18:00"
      }
    },
    {
      "external_id": "38",
      "scp": "1034",
      "name": "Климент",
      "latitude": 43.626875,
      "longitude": 27.017468,
      "temperature_air": 22.294399,
      "temperature_road": 32.279793,
      "humidity": 88.247086,
      "pressure": 978.594421,
      "wind_speed": 9.927904,
      "wind_direction": "194.674194",
      "precipitation": 0,
      "measured_at": "2026-07-20T20:18:00.000Z",
      "captured_from": "https://bgtoll.bg/index.php/mto/data",
      "source_extra": {
        "station_id": 38,
        "scp": 1034,
        "name": "Климент",
        "nameENG": "Kliment",
        "lat": 43.626875,
        "lon": 27.017468,
        "air": 22.294399,
        "surface": 32.279793,
        "humidity": 88.247086,
        "pressure": 978.594421,
        "wind": 9.927904,
        "wind_dir": 194.674194,
        "time": "2026-07-20 20:18:00"
      }
    },
    {
      "external_id": "40",
      "scp": "1036",
      "name": "Петолъчката Зимница",
      "latitude": 42.645258,
      "longitude": 26.667003,
      "temperature_air": 21.164944,
      "temperature_road": 0,
      "humidity": 88.517593,
      "pressure": 997.45343,
      "wind_speed": 3.808695,
      "wind_direction": "17.353577",
      "precipitation": 0,
      "measured_at": "2026-07-20T20:18:00.000Z",
      "captured_from": "https://bgtoll.bg/index.php/mto/data",
      "source_extra": {
        "station_id": 40,
        "scp": 1036,
        "name": "Петолъчката Зимница",
        "nameENG": "Petolachkata Zimnitsa",
        "lat": 42.645258,
        "lon": 26.667003,
        "air": 21.164944,
        "surface": 0,
        "humidity": 88.517593,
        "pressure": 997.45343,
        "wind": 3.808695,
        "wind_dir": 17.353577,
        "time": "2026-07-20 20:18:00"
      }
    },
    {
      "external_id": "41",
      "scp": "1037",
      "name": "Ихтиман",
      "latitude": 42.460646,
      "longitude": 23.803156,
      "temperature_air": 17.877674,
      "temperature_road": 0,
      "humidity": 82.350494,
      "pressure": 941.433594,
      "wind_speed": 4.799773,
      "wind_direction": "64.657303",
      "precipitation": 0,
      "measured_at": "2026-07-20T20:18:00.000Z",
      "captured_from": "https://bgtoll.bg/index.php/mto/data",
      "source_extra": {
        "station_id": 41,
        "scp": 1037,
        "name": "Ихтиман",
        "nameENG": "Ihtiman",
        "lat": 42.460646,
        "lon": 23.803156,
        "air": 17.877674,
        "surface": 0,
        "humidity": 82.350494,
        "pressure": 941.433594,
        "wind": 4.799773,
        "wind_dir": 64.657303,
        "time": "2026-07-20 20:18:00"
      }
    },
    {
      "external_id": "42",
      "scp": "1038",
      "name": "Мирово",
      "latitude": 42.379364,
      "longitude": 23.876303,
      "temperature_air": 16.075371,
      "temperature_road": 0,
      "humidity": 98.982224,
      "pressure": 941.489197,
      "wind_speed": 2.73017,
      "wind_direction": "335.765717",
      "precipitation": 0,
      "measured_at": "2026-07-20T20:18:00.000Z",
      "captured_from": "https://bgtoll.bg/index.php/mto/data",
      "source_extra": {
        "station_id": 42,
        "scp": 1038,
        "name": "Мирово",
        "nameENG": "Mirovo",
        "lat": 42.379364,
        "lon": 23.876303,
        "air": 16.075371,
        "surface": 0,
        "humidity": 98.982224,
        "pressure": 941.489197,
        "wind": 2.73017,
        "wind_dir": 335.765717,
        "time": "2026-07-20 20:18:00"
      }
    },
    {
      "external_id": "44",
      "scp": "1040",
      "name": "Мало конаре",
      "latitude": 42.185589,
      "longitude": 24.413111,
      "temperature_air": 25.109529,
      "temperature_road": 0,
      "humidity": 54.238289,
      "pressure": 993.857971,
      "wind_speed": 16.257734,
      "wind_direction": "262.911255",
      "precipitation": 0,
      "measured_at": "2026-07-20T20:18:00.000Z",
      "captured_from": "https://bgtoll.bg/index.php/mto/data",
      "source_extra": {
        "station_id": 44,
        "scp": 1040,
        "name": "Мало конаре",
        "nameENG": "Malo konare",
        "lat": 42.185589,
        "lon": 24.413111,
        "air": 25.109529,
        "surface": 0,
        "humidity": 54.238289,
        "pressure": 993.857971,
        "wind": 16.257734,
        "wind_dir": 262.911255,
        "time": "2026-07-20 20:18:00"
      }
    },
    {
      "external_id": "45",
      "scp": "1041",
      "name": "Първомай",
      "latitude": 42.08145,
      "longitude": 25.183588,
      "temperature_air": 19.426332,
      "temperature_road": 32.263264,
      "humidity": 96.639687,
      "pressure": 999.733032,
      "wind_speed": 14.649971,
      "wind_direction": "243.924957",
      "precipitation": 0,
      "measured_at": "2026-07-20T20:19:00.000Z",
      "captured_from": "https://bgtoll.bg/index.php/mto/data",
      "source_extra": {
        "station_id": 45,
        "scp": 1041,
        "name": "Първомай",
        "nameENG": "Parvomay",
        "lat": 42.08145,
        "lon": 25.183588,
        "air": 19.426332,
        "surface": 32.263264,
        "humidity": 96.639687,
        "pressure": 999.733032,
        "wind": 14.649971,
        "wind_dir": 243.924957,
        "time": "2026-07-20 20:19:00"
      }
    },
    {
      "external_id": "46",
      "scp": "1042",
      "name": "Дуранкулак",
      "latitude": 43.733178,
      "longitude": 28.556035,
      "temperature_air": 22.043749,
      "temperature_road": 29.074978,
      "humidity": 87.025558,
      "pressure": 1012.16217,
      "wind_speed": 8.018593,
      "wind_direction": "198.294479",
      "precipitation": 0,
      "measured_at": "2026-07-20T20:19:00.000Z",
      "captured_from": "https://bgtoll.bg/index.php/mto/data",
      "source_extra": {
        "station_id": 46,
        "scp": 1042,
        "name": "Дуранкулак",
        "nameENG": "Durankulak",
        "lat": 43.733178,
        "lon": 28.556035,
        "air": 22.043749,
        "surface": 29.074978,
        "humidity": 87.025558,
        "pressure": 1012.16217,
        "wind": 8.018593,
        "wind_dir": 198.294479,
        "time": "2026-07-20 20:19:00"
      }
    },
    {
      "external_id": "47",
      "scp": "1043",
      "name": "Балчик",
      "latitude": 43.436923,
      "longitude": 28.153246,
      "temperature_air": 22.097319,
      "temperature_road": 26.564939,
      "humidity": 85.800377,
      "pressure": 991.645935,
      "wind_speed": 3.867319,
      "wind_direction": "157.282883",
      "precipitation": 0,
      "measured_at": "2026-07-20T20:19:00.000Z",
      "captured_from": "https://bgtoll.bg/index.php/mto/data",
      "source_extra": {
        "station_id": 47,
        "scp": 1043,
        "name": "Балчик",
        "nameENG": "Balchik",
        "lat": 43.436923,
        "lon": 28.153246,
        "air": 22.097319,
        "surface": 26.564939,
        "humidity": 85.800377,
        "pressure": 991.645935,
        "wind": 3.867319,
        "wind_dir": 157.282883,
        "time": "2026-07-20 20:19:00"
      }
    },
    {
      "external_id": "48",
      "scp": "1044",
      "name": "Гъмзово",
      "latitude": 44.092957,
      "longitude": 22.754544,
      "temperature_air": 23.356401,
      "temperature_road": 29.047001,
      "humidity": 56.023895,
      "pressure": 995.799194,
      "wind_speed": 8.307364,
      "wind_direction": "268.976898",
      "precipitation": 0,
      "measured_at": "2026-07-20T20:19:00.000Z",
      "captured_from": "https://bgtoll.bg/index.php/mto/data",
      "source_extra": {
        "station_id": 48,
        "scp": 1044,
        "name": "Гъмзово",
        "nameENG": "Gamzovo",
        "lat": 44.092957,
        "lon": 22.754544,
        "air": 23.356401,
        "surface": 29.047001,
        "humidity": 56.023895,
        "pressure": 995.799194,
        "wind": 8.307364,
        "wind_dir": 268.976898,
        "time": "2026-07-20 20:19:00"
      }
    },
    {
      "external_id": "49",
      "scp": "1045",
      "name": "Борован",
      "latitude": 43.431844,
      "longitude": 23.736628,
      "temperature_air": 24.059305,
      "temperature_road": 36.452225,
      "humidity": 59.969269,
      "pressure": 992.484375,
      "wind_speed": 4.623353,
      "wind_direction": "27.826588",
      "precipitation": 0,
      "measured_at": "2026-07-20T20:19:00.000Z",
      "captured_from": "https://bgtoll.bg/index.php/mto/data",
      "source_extra": {
        "station_id": 49,
        "scp": 1045,
        "name": "Борован",
        "nameENG": "Borovan",
        "lat": 43.431844,
        "lon": 23.736628,
        "air": 24.059305,
        "surface": 36.452225,
        "humidity": 59.969269,
        "pressure": 992.484375,
        "wind": 4.623353,
        "wind_dir": 27.826588,
        "time": "2026-07-20 20:19:00"
      }
    },
    {
      "external_id": "5",
      "scp": "1004",
      "name": "Чурек",
      "latitude": 42.77861,
      "longitude": 23.736149,
      "temperature_air": 23.996946,
      "temperature_road": 0,
      "humidity": 0,
      "pressure": 926.642273,
      "wind_speed": 2.654353,
      "wind_direction": "150.514465",
      "precipitation": 0,
      "measured_at": "2026-07-20T20:30:00.000Z",
      "captured_from": "https://bgtoll.bg/index.php/mto/data",
      "source_extra": {
        "station_id": 5,
        "scp": 1004,
        "name": "Чурек",
        "nameENG": "Churek",
        "lat": 42.77861,
        "lon": 23.736149,
        "air": 23.996946,
        "surface": 0,
        "humidity": 0,
        "pressure": 926.642273,
        "wind": 2.654353,
        "wind_dir": 150.514465,
        "time": "2026-07-20 20:30:00"
      }
    },
    {
      "external_id": "51",
      "scp": "1047",
      "name": "Мраморен",
      "latitude": 43.300159,
      "longitude": 23.663008,
      "temperature_air": 22.996481,
      "temperature_road": 0,
      "humidity": 64.253586,
      "pressure": 982.448669,
      "wind_speed": 2.737956,
      "wind_direction": "296.606964",
      "precipitation": 0,
      "measured_at": "2026-07-20T20:19:00.000Z",
      "captured_from": "https://bgtoll.bg/index.php/mto/data",
      "source_extra": {
        "station_id": 51,
        "scp": 1047,
        "name": "Мраморен",
        "nameENG": "Mramoren",
        "lat": 43.300159,
        "lon": 23.663008,
        "air": 22.996481,
        "surface": 0,
        "humidity": 64.253586,
        "pressure": 982.448669,
        "wind": 2.737956,
        "wind_dir": 296.606964,
        "time": "2026-07-20 20:19:00"
      }
    },
    {
      "external_id": "52",
      "scp": "1048",
      "name": "Садово",
      "latitude": 41.507193,
      "longitude": 23.814894,
      "temperature_air": 17.191401,
      "temperature_road": 0,
      "humidity": 100,
      "pressure": 959.62085,
      "wind_speed": 5.826681,
      "wind_direction": "262.037964",
      "precipitation": 0,
      "measured_at": "2026-07-20T20:19:00.000Z",
      "captured_from": "https://bgtoll.bg/index.php/mto/data",
      "source_extra": {
        "station_id": 52,
        "scp": 1048,
        "name": "Садово",
        "nameENG": "Sadovo",
        "lat": 41.507193,
        "lon": 23.814894,
        "air": 17.191401,
        "surface": 0,
        "humidity": 100,
        "pressure": 959.62085,
        "wind": 5.826681,
        "wind_dir": 262.037964,
        "time": "2026-07-20 20:19:00"
      }
    },
    {
      "external_id": "54",
      "scp": "1050",
      "name": "Одринци",
      "latitude": 43.539778,
      "longitude": 27.709242,
      "temperature_air": 19.955029,
      "temperature_road": 0,
      "humidity": 95.541069,
      "pressure": 990.325317,
      "wind_speed": 1.759597,
      "wind_direction": "69.623657",
      "precipitation": 0,
      "measured_at": "2026-07-20T20:19:00.000Z",
      "captured_from": "https://bgtoll.bg/index.php/mto/data",
      "source_extra": {
        "station_id": 54,
        "scp": 1050,
        "name": "Одринци",
        "nameENG": "Odrintsi",
        "lat": 43.539778,
        "lon": 27.709242,
        "air": 19.955029,
        "surface": 0,
        "humidity": 95.541069,
        "pressure": 990.325317,
        "wind": 1.759597,
        "wind_dir": 69.623657,
        "time": "2026-07-20 20:19:00"
      }
    },
    {
      "external_id": "55",
      "scp": "1051",
      "name": "Кардам",
      "latitude": 43.748849,
      "longitude": 28.095555,
      "temperature_air": 20.311573,
      "temperature_road": 25.78842,
      "humidity": 94.031357,
      "pressure": 994.983582,
      "wind_speed": 0,
      "wind_direction": "0",
      "precipitation": 0,
      "measured_at": "2026-07-20T20:20:00.000Z",
      "captured_from": "https://bgtoll.bg/index.php/mto/data",
      "source_extra": {
        "station_id": 55,
        "scp": 1051,
        "name": "Кардам",
        "nameENG": "Kardam",
        "lat": 43.748849,
        "lon": 28.095555,
        "air": 20.311573,
        "surface": 25.78842,
        "humidity": 94.031357,
        "pressure": 994.983582,
        "wind": 0,
        "wind_dir": 0,
        "time": "2026-07-20 20:20:00"
      }
    },
    {
      "external_id": "56",
      "scp": "1052",
      "name": "Стожер",
      "latitude": 43.441145,
      "longitude": 27.825259,
      "temperature_air": 20.329945,
      "temperature_road": 25.272594,
      "humidity": 88.98597,
      "pressure": 979.284363,
      "wind_speed": 8.407938,
      "wind_direction": "138.926025",
      "precipitation": 0,
      "measured_at": "2026-07-20T20:20:00.000Z",
      "captured_from": "https://bgtoll.bg/index.php/mto/data",
      "source_extra": {
        "station_id": 56,
        "scp": 1052,
        "name": "Стожер",
        "nameENG": "Stozher",
        "lat": 43.441145,
        "lon": 27.825259,
        "air": 20.329945,
        "surface": 25.272594,
        "humidity": 88.98597,
        "pressure": 979.284363,
        "wind": 8.407938,
        "wind_dir": 138.926025,
        "time": "2026-07-20 20:20:00"
      }
    },
    {
      "external_id": "57",
      "scp": "1053",
      "name": "Пишурката",
      "latitude": 43.65801,
      "longitude": 23.250177,
      "temperature_air": 22.478878,
      "temperature_road": 29.477146,
      "humidity": 67.39344,
      "pressure": 997.264709,
      "wind_speed": 3.375661,
      "wind_direction": "304.628998",
      "precipitation": 0,
      "measured_at": "2026-07-20T20:20:00.000Z",
      "captured_from": "https://bgtoll.bg/index.php/mto/data",
      "source_extra": {
        "station_id": 57,
        "scp": 1053,
        "name": "Пишурката",
        "nameENG": "Pishurkata",
        "lat": 43.65801,
        "lon": 23.250177,
        "air": 22.478878,
        "surface": 29.477146,
        "humidity": 67.39344,
        "pressure": 997.264709,
        "wind": 3.375661,
        "wind_dir": 304.628998,
        "time": "2026-07-20 20:20:00"
      }
    },
    {
      "external_id": "58",
      "scp": "1054",
      "name": "Брестовец",
      "latitude": 43.361679,
      "longitude": 24.611624,
      "temperature_air": 23.973728,
      "temperature_road": 31.361446,
      "humidity": 58.377277,
      "pressure": 985.203735,
      "wind_speed": 3.324193,
      "wind_direction": "200.552063",
      "precipitation": 0,
      "measured_at": "2026-07-20T20:20:00.000Z",
      "captured_from": "https://bgtoll.bg/index.php/mto/data",
      "source_extra": {
        "station_id": 58,
        "scp": 1054,
        "name": "Брестовец",
        "nameENG": "Brestovets",
        "lat": 43.361679,
        "lon": 24.611624,
        "air": 23.973728,
        "surface": 31.361446,
        "humidity": 58.377277,
        "pressure": 985.203735,
        "wind": 3.324193,
        "wind_dir": 200.552063,
        "time": "2026-07-20 20:20:00"
      }
    },
    {
      "external_id": "59",
      "scp": "1055",
      "name": "Добродан",
      "latitude": 42.961054,
      "longitude": 24.685785,
      "temperature_air": 21.467558,
      "temperature_road": 27.627377,
      "humidity": 79.009949,
      "pressure": 981.460693,
      "wind_speed": 1.20578,
      "wind_direction": "278.881775",
      "precipitation": 0,
      "measured_at": "2026-07-20T20:20:00.000Z",
      "captured_from": "https://bgtoll.bg/index.php/mto/data",
      "source_extra": {
        "station_id": 59,
        "scp": 1055,
        "name": "Добродан",
        "nameENG": "Dobrodan",
        "lat": 42.961054,
        "lon": 24.685785,
        "air": 21.467558,
        "surface": 27.627377,
        "humidity": 79.009949,
        "pressure": 981.460693,
        "wind": 1.20578,
        "wind_dir": 278.881775,
        "time": "2026-07-20 20:20:00"
      }
    },
    {
      "external_id": "6",
      "scp": "1005",
      "name": "Разлив",
      "latitude": 42.907531,
      "longitude": 23.877779,
      "temperature_air": 19.64802,
      "temperature_road": 0,
      "humidity": 85.156075,
      "pressure": 966.356689,
      "wind_speed": 9.887548,
      "wind_direction": "98.700691",
      "precipitation": 0,
      "measured_at": "2026-07-20T20:30:00.000Z",
      "captured_from": "https://bgtoll.bg/index.php/mto/data",
      "source_extra": {
        "station_id": 6,
        "scp": 1005,
        "name": "Разлив",
        "nameENG": "Razliv",
        "lat": 42.907531,
        "lon": 23.877779,
        "air": 19.64802,
        "surface": 0,
        "humidity": 85.156075,
        "pressure": 966.356689,
        "wind": 9.887548,
        "wind_dir": 98.700691,
        "time": "2026-07-20 20:30:00"
      }
    },
    {
      "external_id": "61",
      "scp": "1057",
      "name": "Тертер",
      "latitude": 43.90457,
      "longitude": 26.53674,
      "temperature_air": 24.605085,
      "temperature_road": 31.181637,
      "humidity": 70.772995,
      "pressure": 1000.140442,
      "wind_speed": 4.192381,
      "wind_direction": "219.723358",
      "precipitation": 0,
      "measured_at": "2026-07-20T20:20:00.000Z",
      "captured_from": "https://bgtoll.bg/index.php/mto/data",
      "source_extra": {
        "station_id": 61,
        "scp": 1057,
        "name": "Тертер",
        "nameENG": "Terter",
        "lat": 43.90457,
        "lon": 26.53674,
        "air": 24.605085,
        "surface": 31.181637,
        "humidity": 70.772995,
        "pressure": 1000.140442,
        "wind": 4.192381,
        "wind_dir": 219.723358,
        "time": "2026-07-20 20:20:00"
      }
    },
    {
      "external_id": "62",
      "scp": "1058",
      "name": "Светлен",
      "latitude": 43.314711,
      "longitude": 26.282734,
      "temperature_air": 20.978428,
      "temperature_road": 0,
      "humidity": 87.766541,
      "pressure": 993.322571,
      "wind_speed": 2.690002,
      "wind_direction": "175.648926",
      "precipitation": 0,
      "measured_at": "2026-07-20T20:20:00.000Z",
      "captured_from": "https://bgtoll.bg/index.php/mto/data",
      "source_extra": {
        "station_id": 62,
        "scp": 1058,
        "name": "Светлен",
        "nameENG": "Svetlen",
        "lat": 43.314711,
        "lon": 26.282734,
        "air": 20.978428,
        "surface": 0,
        "humidity": 87.766541,
        "pressure": 993.322571,
        "wind": 2.690002,
        "wind_dir": 175.648926,
        "time": "2026-07-20 20:20:00"
      }
    },
    {
      "external_id": "63",
      "scp": "1059",
      "name": "Асеновец изход",
      "latitude": 42.519781,
      "longitude": 25.960411,
      "temperature_air": 23.699732,
      "temperature_road": 33.538696,
      "humidity": 73.92968,
      "pressure": 997.572937,
      "wind_speed": 1.702472,
      "wind_direction": "281.962646",
      "precipitation": 0,
      "measured_at": "2026-07-20T20:20:00.000Z",
      "captured_from": "https://bgtoll.bg/index.php/mto/data",
      "source_extra": {
        "station_id": 63,
        "scp": 1059,
        "name": "Асеновец  изход",
        "nameENG": "Asenovets exit",
        "lat": 42.519781,
        "lon": 25.960411,
        "air": 23.699732,
        "surface": 33.538696,
        "humidity": 73.92968,
        "pressure": 997.572937,
        "wind": 1.702472,
        "wind_dir": 281.962646,
        "time": "2026-07-20 20:20:00"
      }
    },
    {
      "external_id": "64",
      "scp": "1060",
      "name": "Елена",
      "latitude": 42.918316,
      "longitude": 25.920351,
      "temperature_air": 20.327116,
      "temperature_road": 30.010998,
      "humidity": 93.169899,
      "pressure": 980.843872,
      "wind_speed": 0,
      "wind_direction": "0",
      "precipitation": 0,
      "measured_at": "2026-07-20T20:20:00.000Z",
      "captured_from": "https://bgtoll.bg/index.php/mto/data",
      "source_extra": {
        "station_id": 64,
        "scp": 1060,
        "name": "Елена",
        "nameENG": "Elena",
        "lat": 42.918316,
        "lon": 25.920351,
        "air": 20.327116,
        "surface": 30.010998,
        "humidity": 93.169899,
        "pressure": 980.843872,
        "wind": 0,
        "wind_dir": 0,
        "time": "2026-07-20 20:20:00"
      }
    },
    {
      "external_id": "65",
      "scp": "1061",
      "name": "Войника",
      "latitude": 42.382827,
      "longitude": 26.831974,
      "temperature_air": 22.094215,
      "temperature_road": 31.654402,
      "humidity": 80.034973,
      "pressure": 988.269165,
      "wind_speed": 5.242853,
      "wind_direction": "106.845062",
      "precipitation": 0,
      "measured_at": "2026-07-20T20:21:00.000Z",
      "captured_from": "https://bgtoll.bg/index.php/mto/data",
      "source_extra": {
        "station_id": 65,
        "scp": 1061,
        "name": "Войника",
        "nameENG": "Voynika",
        "lat": 42.382827,
        "lon": 26.831974,
        "air": 22.094215,
        "surface": 31.654402,
        "humidity": 80.034973,
        "pressure": 988.269165,
        "wind": 5.242853,
        "wind_dir": 106.845062,
        "time": "2026-07-20 20:21:00"
      }
    },
    {
      "external_id": "66",
      "scp": "1062",
      "name": "Радецки",
      "latitude": 42.279262,
      "longitude": 26.125522,
      "temperature_air": 22.935705,
      "temperature_road": 30.907972,
      "humidity": 80.510658,
      "pressure": 999.094849,
      "wind_speed": 10.496077,
      "wind_direction": "25.239462",
      "precipitation": 0,
      "measured_at": "2026-07-20T20:21:00.000Z",
      "captured_from": "https://bgtoll.bg/index.php/mto/data",
      "source_extra": {
        "station_id": 66,
        "scp": 1062,
        "name": "Радецки",
        "nameENG": "Radetski",
        "lat": 42.279262,
        "lon": 26.125522,
        "air": 22.935705,
        "surface": 30.907972,
        "humidity": 80.510658,
        "pressure": 999.094849,
        "wind": 10.496077,
        "wind_dir": 25.239462,
        "time": "2026-07-20 20:21:00"
      }
    },
    {
      "external_id": "67",
      "scp": "1063",
      "name": "Брезово",
      "latitude": 42.361168,
      "longitude": 25.079729,
      "temperature_air": 18.471619,
      "temperature_road": 0,
      "humidity": 96.807632,
      "pressure": 986.976318,
      "wind_speed": 5.189793,
      "wind_direction": "340.28949",
      "precipitation": 0,
      "measured_at": "2026-07-20T20:21:00.000Z",
      "captured_from": "https://bgtoll.bg/index.php/mto/data",
      "source_extra": {
        "station_id": 67,
        "scp": 1063,
        "name": "Брезово",
        "nameENG": "Brezovo",
        "lat": 42.361168,
        "lon": 25.079729,
        "air": 18.471619,
        "surface": 0,
        "humidity": 96.807632,
        "pressure": 986.976318,
        "wind": 5.189793,
        "wind_dir": 340.28949,
        "time": "2026-07-20 20:21:00"
      }
    },
    {
      "external_id": "68",
      "scp": "1064",
      "name": "Червен",
      "latitude": 41.944329,
      "longitude": 24.962951,
      "temperature_air": 21.091347,
      "temperature_road": 0,
      "humidity": 79.334724,
      "pressure": 970.404053,
      "wind_speed": 0,
      "wind_direction": "0",
      "precipitation": 0,
      "measured_at": "2026-07-20T20:21:00.000Z",
      "captured_from": "https://bgtoll.bg/index.php/mto/data",
      "source_extra": {
        "station_id": 68,
        "scp": 1064,
        "name": "Червен",
        "nameENG": "Cherven",
        "lat": 41.944329,
        "lon": 24.962951,
        "air": 21.091347,
        "surface": 0,
        "humidity": 79.334724,
        "pressure": 970.404053,
        "wind": 0,
        "wind_dir": 0,
        "time": "2026-07-20 20:21:00"
      }
    },
    {
      "external_id": "69",
      "scp": "1065",
      "name": "Паничарево",
      "latitude": 42.274151,
      "longitude": 22.994855,
      "temperature_air": 17.573902,
      "temperature_road": 25.608799,
      "humidity": 90.878845,
      "pressure": 957.035278,
      "wind_speed": 6.425626,
      "wind_direction": "251.856567",
      "precipitation": 0,
      "measured_at": "2026-07-20T20:21:00.000Z",
      "captured_from": "https://bgtoll.bg/index.php/mto/data",
      "source_extra": {
        "station_id": 69,
        "scp": 1065,
        "name": "Паничарево",
        "nameENG": "Panicharevo",
        "lat": 42.274151,
        "lon": 22.994855,
        "air": 17.573902,
        "surface": 25.608799,
        "humidity": 90.878845,
        "pressure": 957.035278,
        "wind": 6.425626,
        "wind_dir": 251.856567,
        "time": "2026-07-20 20:21:00"
      }
    },
    {
      "external_id": "7",
      "scp": "1006",
      "name": "Белокопитово",
      "latitude": 43.337204,
      "longitude": 26.900232,
      "temperature_air": 20.46023,
      "temperature_road": 26.413309,
      "humidity": 97.03698,
      "pressure": 991.501404,
      "wind_speed": 2.271985,
      "wind_direction": "223.949097",
      "precipitation": 0,
      "measured_at": "2026-07-20T20:30:00.000Z",
      "captured_from": "https://bgtoll.bg/index.php/mto/data",
      "source_extra": {
        "station_id": 7,
        "scp": 1006,
        "name": "Белокопитово",
        "nameENG": "Belokopitovo",
        "lat": 43.337204,
        "lon": 26.900232,
        "air": 20.46023,
        "surface": 26.413309,
        "humidity": 97.03698,
        "pressure": 991.501404,
        "wind": 2.271985,
        "wind_dir": 223.949097,
        "time": "2026-07-20 20:30:00"
      }
    },
    {
      "external_id": "70",
      "scp": "1066",
      "name": "Слишовци",
      "latitude": 42.806608,
      "longitude": 22.477234,
      "temperature_air": 14.142679,
      "temperature_road": 23.243658,
      "humidity": 93.760033,
      "pressure": 928.459106,
      "wind_speed": 4.350079,
      "wind_direction": "280.500977",
      "precipitation": 0,
      "measured_at": "2026-07-20T20:21:00.000Z",
      "captured_from": "https://bgtoll.bg/index.php/mto/data",
      "source_extra": {
        "station_id": 70,
        "scp": 1066,
        "name": "Слишовци",
        "nameENG": "Slishovtsi",
        "lat": 42.806608,
        "lon": 22.477234,
        "air": 14.142679,
        "surface": 23.243658,
        "humidity": 93.760033,
        "pressure": 928.459106,
        "wind": 4.350079,
        "wind_dir": 280.500977,
        "time": "2026-07-20 20:21:00"
      }
    },
    {
      "external_id": "71",
      "scp": "1067",
      "name": "Перник",
      "latitude": 42.630555,
      "longitude": 23.015927,
      "temperature_air": 16.294022,
      "temperature_road": 0,
      "humidity": 94.352455,
      "pressure": 935.51532,
      "wind_speed": 15.502256,
      "wind_direction": "258.580444",
      "precipitation": 0,
      "measured_at": "2026-07-20T20:21:00.000Z",
      "captured_from": "https://bgtoll.bg/index.php/mto/data",
      "source_extra": {
        "station_id": 71,
        "scp": 1067,
        "name": "Перник",
        "nameENG": "Pernik",
        "lat": 42.630555,
        "lon": 23.015927,
        "air": 16.294022,
        "surface": 0,
        "humidity": 94.352455,
        "pressure": 935.51532,
        "wind": 15.502256,
        "wind_dir": 258.580444,
        "time": "2026-07-20 20:21:00"
      }
    },
    {
      "external_id": "72",
      "scp": "1068",
      "name": "Труд",
      "latitude": 42.244317,
      "longitude": 24.723602,
      "temperature_air": 19.46073,
      "temperature_road": 30.427847,
      "humidity": 100,
      "pressure": 996.268799,
      "wind_speed": 7.888606,
      "wind_direction": "214.601822",
      "precipitation": 0,
      "measured_at": "2026-07-20T20:21:00.000Z",
      "captured_from": "https://bgtoll.bg/index.php/mto/data",
      "source_extra": {
        "station_id": 72,
        "scp": 1068,
        "name": "Труд",
        "nameENG": "Trud",
        "lat": 42.244317,
        "lon": 24.723602,
        "air": 19.46073,
        "surface": 30.427847,
        "humidity": 100,
        "pressure": 996.268799,
        "wind": 7.888606,
        "wind_dir": 214.601822,
        "time": "2026-07-20 20:21:00"
      }
    },
    {
      "external_id": "73",
      "scp": "1069",
      "name": "Съдиево",
      "latitude": 42.532905,
      "longitude": 26.08247,
      "temperature_air": 22.743612,
      "temperature_road": 0,
      "humidity": 79.52076,
      "pressure": 997.329712,
      "wind_speed": 4.101368,
      "wind_direction": "332.716309",
      "precipitation": 0,
      "measured_at": "2026-07-20T20:21:00.000Z",
      "captured_from": "https://bgtoll.bg/index.php/mto/data",
      "source_extra": {
        "station_id": 73,
        "scp": 1069,
        "name": "Съдиево",
        "nameENG": "Sadievo",
        "lat": 42.532905,
        "lon": 26.08247,
        "air": 22.743612,
        "surface": 0,
        "humidity": 79.52076,
        "pressure": 997.329712,
        "wind": 4.101368,
        "wind_dir": 332.716309,
        "time": "2026-07-20 20:21:00"
      }
    },
    {
      "external_id": "74",
      "scp": "1070",
      "name": "Средище",
      "latitude": 43.911104,
      "longitude": 27.477847,
      "temperature_air": 22.015341,
      "temperature_road": 31.351114,
      "humidity": 88.796104,
      "pressure": 992.578613,
      "wind_speed": 9.958525,
      "wind_direction": "170.263611",
      "precipitation": 0,
      "measured_at": "2026-07-20T20:21:00.000Z",
      "captured_from": "https://bgtoll.bg/index.php/mto/data",
      "source_extra": {
        "station_id": 74,
        "scp": 1070,
        "name": "Средище",
        "nameENG": "Sredishte",
        "lat": 43.911104,
        "lon": 27.477847,
        "air": 22.015341,
        "surface": 31.351114,
        "humidity": 88.796104,
        "pressure": 992.578613,
        "wind": 9.958525,
        "wind_dir": 170.263611,
        "time": "2026-07-20 20:21:00"
      }
    },
    {
      "external_id": "75",
      "scp": "1071",
      "name": "Баячево",
      "latitude": 43.219807,
      "longitude": 26.657023,
      "temperature_air": 22.070156,
      "temperature_road": 32.542137,
      "humidity": 87.114418,
      "pressure": 991.6026,
      "wind_speed": 1.232351,
      "wind_direction": "204.598785",
      "precipitation": 0,
      "measured_at": "2026-07-20T20:22:00.000Z",
      "captured_from": "https://bgtoll.bg/index.php/mto/data",
      "source_extra": {
        "station_id": 75,
        "scp": 1071,
        "name": "Баячево",
        "nameENG": "Bayachevo",
        "lat": 43.219807,
        "lon": 26.657023,
        "air": 22.070156,
        "surface": 32.542137,
        "humidity": 87.114418,
        "pressure": 991.6026,
        "wind": 1.232351,
        "wind_dir": 204.598785,
        "time": "2026-07-20 20:22:00"
      }
    },
    {
      "external_id": "76",
      "scp": "1072",
      "name": "Коларово",
      "latitude": 41.970639,
      "longitude": 26.002254,
      "temperature_air": 25.418575,
      "temperature_road": 33.839573,
      "humidity": 73.138474,
      "pressure": 987.939575,
      "wind_speed": 2.72783,
      "wind_direction": "25.148132",
      "precipitation": 0,
      "measured_at": "2026-07-20T20:22:00.000Z",
      "captured_from": "https://bgtoll.bg/index.php/mto/data",
      "source_extra": {
        "station_id": 76,
        "scp": 1072,
        "name": "Коларово",
        "nameENG": "Kolarovo",
        "lat": 41.970639,
        "lon": 26.002254,
        "air": 25.418575,
        "surface": 33.839573,
        "humidity": 73.138474,
        "pressure": 987.939575,
        "wind": 2.72783,
        "wind_dir": 25.148132,
        "time": "2026-07-20 20:22:00"
      }
    },
    {
      "external_id": "77",
      "scp": "1073",
      "name": "ГКПП Капитан Петко Войвода",
      "latitude": 41.763993,
      "longitude": 26.158672,
      "temperature_air": 25.699596,
      "temperature_road": 33.716511,
      "humidity": 67.784332,
      "pressure": 1007.44043,
      "wind_speed": 4.161106,
      "wind_direction": "150.328537",
      "precipitation": 0,
      "measured_at": "2026-07-20T20:22:00.000Z",
      "captured_from": "https://bgtoll.bg/index.php/mto/data",
      "source_extra": {
        "station_id": 77,
        "scp": 1073,
        "name": "ГКПП Капитан Петко Войвода",
        "nameENG": "BCCP Kapitan Petko Voyvoda",
        "lat": 41.763993,
        "lon": 26.158672,
        "air": 25.699596,
        "surface": 33.716511,
        "humidity": 67.784332,
        "pressure": 1007.44043,
        "wind": 4.161106,
        "wind_dir": 150.328537,
        "time": "2026-07-20 20:22:00"
      }
    },
    {
      "external_id": "78",
      "scp": "1074",
      "name": "Бързия",
      "latitude": 43.120328,
      "longitude": 23.122952,
      "temperature_air": 17.963129,
      "temperature_road": 20.709858,
      "humidity": 51.597805,
      "pressure": 864.76825,
      "wind_speed": 2.186178,
      "wind_direction": "271.392273",
      "precipitation": 0,
      "measured_at": "2026-07-20T20:22:00.000Z",
      "captured_from": "https://bgtoll.bg/index.php/mto/data",
      "source_extra": {
        "station_id": 78,
        "scp": 1074,
        "name": "Бързия",
        "nameENG": "Barziya",
        "lat": 43.120328,
        "lon": 23.122952,
        "air": 17.963129,
        "surface": 20.709858,
        "humidity": 51.597805,
        "pressure": 864.76825,
        "wind": 2.186178,
        "wind_dir": 271.392273,
        "time": "2026-07-20 20:22:00"
      }
    },
    {
      "external_id": "8",
      "scp": "1007",
      "name": "Девня",
      "latitude": 43.227186,
      "longitude": 27.583581,
      "temperature_air": 21.329876,
      "temperature_road": 0,
      "humidity": 83.630791,
      "pressure": 1010.814636,
      "wind_speed": 3.587389,
      "wind_direction": "283.912231",
      "precipitation": 0,
      "measured_at": "2026-07-20T20:30:00.000Z",
      "captured_from": "https://bgtoll.bg/index.php/mto/data",
      "source_extra": {
        "station_id": 8,
        "scp": 1007,
        "name": "Девня",
        "nameENG": "Devnya",
        "lat": 43.227186,
        "lon": 27.583581,
        "air": 21.329876,
        "surface": 0,
        "humidity": 83.630791,
        "pressure": 1010.814636,
        "wind": 3.587389,
        "wind_dir": 283.912231,
        "time": "2026-07-20 20:30:00"
      }
    },
    {
      "external_id": "81",
      "scp": "1077",
      "name": "Чепеларе",
      "latitude": 41.699634,
      "longitude": 24.693263,
      "temperature_air": 15.270412,
      "temperature_road": 0,
      "humidity": 98.311783,
      "pressure": 889.552429,
      "wind_speed": 1.661996,
      "wind_direction": "71.583679",
      "precipitation": 0,
      "measured_at": "2026-07-20T20:22:00.000Z",
      "captured_from": "https://bgtoll.bg/index.php/mto/data",
      "source_extra": {
        "station_id": 81,
        "scp": 1077,
        "name": "Чепеларе",
        "nameENG": "Chepelare",
        "lat": 41.699634,
        "lon": 24.693263,
        "air": 15.270412,
        "surface": 0,
        "humidity": 98.311783,
        "pressure": 889.552429,
        "wind": 1.661996,
        "wind_dir": 71.583679,
        "time": "2026-07-20 20:22:00"
      }
    },
    {
      "external_id": "82",
      "scp": "1078",
      "name": "Равнища",
      "latitude": 41.539991,
      "longitude": 24.906576,
      "temperature_air": 18.521431,
      "temperature_road": 0,
      "humidity": 99.044739,
      "pressure": 941.931091,
      "wind_speed": 1.740055,
      "wind_direction": "268.875122",
      "precipitation": 0,
      "measured_at": "2026-07-20T20:22:00.000Z",
      "captured_from": "https://bgtoll.bg/index.php/mto/data",
      "source_extra": {
        "station_id": 82,
        "scp": 1078,
        "name": "Равнища",
        "nameENG": "Ravnishta",
        "lat": 41.539991,
        "lon": 24.906576,
        "air": 18.521431,
        "surface": 0,
        "humidity": 99.044739,
        "pressure": 941.931091,
        "wind": 1.740055,
        "wind_dir": 268.875122,
        "time": "2026-07-20 20:22:00"
      }
    },
    {
      "external_id": "83",
      "scp": "1079",
      "name": "Добри дол",
      "latitude": 43.771699,
      "longitude": 22.992963,
      "temperature_air": 24.99716,
      "temperature_road": 32.445244,
      "humidity": 55.731834,
      "pressure": 1010.408386,
      "wind_speed": 8.221905,
      "wind_direction": "263.254364",
      "precipitation": 0,
      "measured_at": "2026-07-20T20:22:00.000Z",
      "captured_from": "https://bgtoll.bg/index.php/mto/data",
      "source_extra": {
        "station_id": 83,
        "scp": 1079,
        "name": "Добри дол",
        "nameENG": "Dobri dol",
        "lat": 43.771699,
        "lon": 22.992963,
        "air": 24.99716,
        "surface": 32.445244,
        "humidity": 55.731834,
        "pressure": 1010.408386,
        "wind": 8.221905,
        "wind_dir": 263.254364,
        "time": "2026-07-20 20:22:00"
      }
    },
    {
      "external_id": "84",
      "scp": "1080",
      "name": "Биволаре",
      "latitude": 43.498796,
      "longitude": 24.548433,
      "temperature_air": 23.703459,
      "temperature_road": 0,
      "humidity": 60.118717,
      "pressure": 1010.233765,
      "wind_speed": 3.284766,
      "wind_direction": "160.184998",
      "precipitation": 0,
      "measured_at": "2026-07-20T20:22:00.000Z",
      "captured_from": "https://bgtoll.bg/index.php/mto/data",
      "source_extra": {
        "station_id": 84,
        "scp": 1080,
        "name": "Биволаре",
        "nameENG": "Bivolare",
        "lat": 43.498796,
        "lon": 24.548433,
        "air": 23.703459,
        "surface": 0,
        "humidity": 60.118717,
        "pressure": 1010.233765,
        "wind": 3.284766,
        "wind_dir": 160.184998,
        "time": "2026-07-20 20:22:00"
      }
    },
    {
      "external_id": "85",
      "scp": "1081",
      "name": "Долно Дряново",
      "latitude": 41.581809,
      "longitude": 23.895556,
      "temperature_air": 15.704154,
      "temperature_road": 25.911871,
      "humidity": 98.327087,
      "pressure": 929.555725,
      "wind_speed": 4.940908,
      "wind_direction": "280.470856",
      "precipitation": 0,
      "measured_at": "2026-07-20T20:23:00.000Z",
      "captured_from": "https://bgtoll.bg/index.php/mto/data",
      "source_extra": {
        "station_id": 85,
        "scp": 1081,
        "name": "Долно Дряново",
        "nameENG": "Dolno Dryanovo",
        "lat": 41.581809,
        "lon": 23.895556,
        "air": 15.704154,
        "surface": 25.911871,
        "humidity": 98.327087,
        "pressure": 929.555725,
        "wind": 4.940908,
        "wind_dir": 280.470856,
        "time": "2026-07-20 20:23:00"
      }
    },
    {
      "external_id": "86",
      "scp": "1082",
      "name": "Струмешница",
      "latitude": 41.397228,
      "longitude": 23.057641,
      "temperature_air": 19.574736,
      "temperature_road": 30.907263,
      "humidity": 100,
      "pressure": 997.449524,
      "wind_speed": 2.068857,
      "wind_direction": "350.72821",
      "precipitation": 0,
      "measured_at": "2026-07-20T20:23:00.000Z",
      "captured_from": "https://bgtoll.bg/index.php/mto/data",
      "source_extra": {
        "station_id": 86,
        "scp": 1082,
        "name": "Струмешница",
        "nameENG": "Strumeshnitsa",
        "lat": 41.397228,
        "lon": 23.057641,
        "air": 19.574736,
        "surface": 30.907263,
        "humidity": 100,
        "pressure": 997.449524,
        "wind": 2.068857,
        "wind_dir": 350.72821,
        "time": "2026-07-20 20:23:00"
      }
    },
    {
      "external_id": "87",
      "scp": "1083",
      "name": "Калиманци",
      "latitude": 41.453887,
      "longitude": 23.439492,
      "temperature_air": 23.353401,
      "temperature_road": 33.798523,
      "humidity": 65.59977,
      "pressure": 995.851929,
      "wind_speed": 0,
      "wind_direction": "0",
      "precipitation": 0,
      "measured_at": "2026-07-20T20:23:00.000Z",
      "captured_from": "https://bgtoll.bg/index.php/mto/data",
      "source_extra": {
        "station_id": 87,
        "scp": 1083,
        "name": "Калиманци",
        "nameENG": "Kalimantsi",
        "lat": 41.453887,
        "lon": 23.439492,
        "air": 23.353401,
        "surface": 33.798523,
        "humidity": 65.59977,
        "pressure": 995.851929,
        "wind": 0,
        "wind_dir": 0,
        "time": "2026-07-20 20:23:00"
      }
    },
    {
      "external_id": "88",
      "scp": "1084",
      "name": "Добромир",
      "latitude": 42.955746,
      "longitude": 27.288908,
      "temperature_air": 21.957241,
      "temperature_road": 0,
      "humidity": 90.860336,
      "pressure": 1005.681091,
      "wind_speed": 2.251474,
      "wind_direction": "353.504669",
      "precipitation": 0,
      "measured_at": "2026-07-20T20:23:00.000Z",
      "captured_from": "https://bgtoll.bg/index.php/mto/data",
      "source_extra": {
        "station_id": 88,
        "scp": 1084,
        "name": "Добромир",
        "nameENG": "Dobromir",
        "lat": 42.955746,
        "lon": 27.288908,
        "air": 21.957241,
        "surface": 0,
        "humidity": 90.860336,
        "pressure": 1005.681091,
        "wind": 2.251474,
        "wind_dir": 353.504669,
        "time": "2026-07-20 20:23:00"
      }
    },
    {
      "external_id": "89",
      "scp": "1085",
      "name": "Александрово",
      "latitude": 43.269519,
      "longitude": 24.956711,
      "temperature_air": 19.478033,
      "temperature_road": 29.917698,
      "humidity": 97.922829,
      "pressure": 1004.715027,
      "wind_speed": 9.137362,
      "wind_direction": "155.638336",
      "precipitation": 0,
      "measured_at": "2026-07-20T20:23:00.000Z",
      "captured_from": "https://bgtoll.bg/index.php/mto/data",
      "source_extra": {
        "station_id": 89,
        "scp": 1085,
        "name": "Александрово",
        "nameENG": "Aleksandrovo",
        "lat": 43.269519,
        "lon": 24.956711,
        "air": 19.478033,
        "surface": 29.917698,
        "humidity": 97.922829,
        "pressure": 1004.715027,
        "wind": 9.137362,
        "wind_dir": 155.638336,
        "time": "2026-07-20 20:23:00"
      }
    },
    {
      "external_id": "9",
      "scp": "1008",
      "name": "Игнатиево",
      "latitude": 43.240614,
      "longitude": 27.781228,
      "temperature_air": 22.446093,
      "temperature_road": 0,
      "humidity": 82.098137,
      "pressure": 1010.072388,
      "wind_speed": 5.77432,
      "wind_direction": "22.40387",
      "precipitation": 0,
      "measured_at": "2026-07-20T20:30:00.000Z",
      "captured_from": "https://bgtoll.bg/index.php/mto/data",
      "source_extra": {
        "station_id": 9,
        "scp": 1008,
        "name": "Игнатиево",
        "nameENG": "Ignatievo",
        "lat": 43.240614,
        "lon": 27.781228,
        "air": 22.446093,
        "surface": 0,
        "humidity": 82.098137,
        "pressure": 1010.072388,
        "wind": 5.77432,
        "wind_dir": 22.40387,
        "time": "2026-07-20 20:30:00"
      }
    },
    {
      "external_id": "90",
      "scp": "1086",
      "name": "Градище",
      "latitude": 43.321231,
      "longitude": 25.206289,
      "temperature_air": 24.98127,
      "temperature_road": 28.262045,
      "humidity": 62.198048,
      "pressure": 1005.363586,
      "wind_speed": 20.890163,
      "wind_direction": "252.104675",
      "precipitation": 0,
      "measured_at": "2026-07-20T20:23:00.000Z",
      "captured_from": "https://bgtoll.bg/index.php/mto/data",
      "source_extra": {
        "station_id": 90,
        "scp": 1086,
        "name": "Градище",
        "nameENG": "Gradishte",
        "lat": 43.321231,
        "lon": 25.206289,
        "air": 24.98127,
        "surface": 28.262045,
        "humidity": 62.198048,
        "pressure": 1005.363586,
        "wind": 20.890163,
        "wind_dir": 252.104675,
        "time": "2026-07-20 20:23:00"
      }
    },
    {
      "external_id": "91",
      "scp": "1087",
      "name": "Садовец",
      "latitude": 43.315137,
      "longitude": 24.358681,
      "temperature_air": 25.100397,
      "temperature_road": 37.835724,
      "humidity": 57.475952,
      "pressure": 1002.64978,
      "wind_speed": 1.894615,
      "wind_direction": "154.68808",
      "precipitation": 0,
      "measured_at": "2026-07-20T20:23:00.000Z",
      "captured_from": "https://bgtoll.bg/index.php/mto/data",
      "source_extra": {
        "station_id": 91,
        "scp": 1087,
        "name": "Садовец",
        "nameENG": "Sadovets",
        "lat": 43.315137,
        "lon": 24.358681,
        "air": 25.100397,
        "surface": 37.835724,
        "humidity": 57.475952,
        "pressure": 1002.64978,
        "wind": 1.894615,
        "wind_dir": 154.68808,
        "time": "2026-07-20 20:23:00"
      }
    },
    {
      "external_id": "92",
      "scp": "1088",
      "name": "Кнежа",
      "latitude": 43.512519,
      "longitude": 24.08262,
      "temperature_air": 23.081423,
      "temperature_road": 0,
      "humidity": 64.611595,
      "pressure": 1000.009033,
      "wind_speed": 1.331776,
      "wind_direction": "328.046722",
      "precipitation": 0,
      "measured_at": "2026-07-20T20:23:00.000Z",
      "captured_from": "https://bgtoll.bg/index.php/mto/data",
      "source_extra": {
        "station_id": 92,
        "scp": 1088,
        "name": "Кнежа",
        "nameENG": "Knezha",
        "lat": 43.512519,
        "lon": 24.08262,
        "air": 23.081423,
        "surface": 0,
        "humidity": 64.611595,
        "pressure": 1000.009033,
        "wind": 1.331776,
        "wind_dir": 328.046722,
        "time": "2026-07-20 20:23:00"
      }
    },
    {
      "external_id": "93",
      "scp": "1089",
      "name": "Опан",
      "latitude": 42.116321,
      "longitude": 25.765778,
      "temperature_air": 24.302481,
      "temperature_road": 33.065128,
      "humidity": 75.893059,
      "pressure": 996.854858,
      "wind_speed": 21.287054,
      "wind_direction": "255.702515",
      "precipitation": 0,
      "measured_at": "2026-07-20T20:23:00.000Z",
      "captured_from": "https://bgtoll.bg/index.php/mto/data",
      "source_extra": {
        "station_id": 93,
        "scp": 1089,
        "name": "Опан",
        "nameENG": "Opan",
        "lat": 42.116321,
        "lon": 25.765778,
        "air": 24.302481,
        "surface": 33.065128,
        "humidity": 75.893059,
        "pressure": 996.854858,
        "wind": 21.287054,
        "wind_dir": 255.702515,
        "time": "2026-07-20 20:23:00"
      }
    },
    {
      "external_id": "94",
      "scp": "1090",
      "name": "Долно войводино",
      "latitude": 41.804442,
      "longitude": 25.568942,
      "temperature_air": 25.172838,
      "temperature_road": 29.229921,
      "humidity": 68.875244,
      "pressure": 992.560547,
      "wind_speed": 0,
      "wind_direction": "0",
      "precipitation": 0,
      "measured_at": "2026-07-20T20:23:00.000Z",
      "captured_from": "https://bgtoll.bg/index.php/mto/data",
      "source_extra": {
        "station_id": 94,
        "scp": 1090,
        "name": "Долно войводино",
        "nameENG": "Dolno voyvodino",
        "lat": 41.804442,
        "lon": 25.568942,
        "air": 25.172838,
        "surface": 29.229921,
        "humidity": 68.875244,
        "pressure": 992.560547,
        "wind": 0,
        "wind_dir": 0,
        "time": "2026-07-20 20:23:00"
      }
    }
  ],
  "diagnostics": {
    "matched_responses": [
      {
        "url": "https://bgtoll.bg/index.php/mto/data",
        "status": 200,
        "resourceType": "fetch",
        "contentType": "application/json; charset=utf-8",
        "added": 95
      }
    ],
    "fetch_attempts": [],
    "page_status": 200
  }
}